methodokta/__init__.py
methodokta/core/__init__.py
methodokta/core/datetime_utils.py
methodokta/core/pydantic_utilities.py
methodokta/core/serialization.py
methodokta/py.typed
methodokta/resources/__init__.py
methodokta/resources/application/__init__.py
methodokta/resources/application/application.py
methodokta/resources/application/application_report.py
methodokta/resources/application/auth_type.py
methodokta/resources/common/__init__.py
methodokta/resources/common/application_info.py
methodokta/resources/common/group_info.py
methodokta/resources/common/role_info.py
methodokta/resources/common/role_type.py
methodokta/resources/common/status_type.py
methodokta/resources/common/user_info.py
methodokta/resources/device/__init__.py
methodokta/resources/device/device.py
methodokta/resources/device/device_report.py
methodokta/resources/group/__init__.py
methodokta/resources/group/group.py
methodokta/resources/group/group_report.py
methodokta/resources/group/group_type.py
methodokta/resources/login/__init__.py
methodokta/resources/login/login.py
methodokta/resources/login/login_report.py
methodokta/resources/org/__init__.py
methodokta/resources/org/org_info.py
methodokta/resources/org/org_report.py
methodokta/resources/user/__init__.py
methodokta/resources/user/user.py
methodokta/resources/user/user_report.py
methodokta-0.0.11.dist-info/METADATA
methodokta-0.0.11.dist-info/WHEEL
methodokta-0.0.11.dist-info/RECORD
